microviewer/__init__.py
microviewer/crackle.js
microviewer/datacube.js
microviewer/favicon.ico
microviewer/index.html
microviewer/jquery-3.7.0.min.js
microviewer/libcrackle.wasm
microviewer/microviewer.css
microviewer/microviewer.js
microviewer/viz3d.py
microviewer/cursors/exact-active.png
microviewer/cursors/exact.png
microviewer/cursors/large-active.png
microviewer/cursors/large.png
microviewer/cursors/medium-active.png
microviewer/cursors/medium.png
microviewer/cursors/small-active.png
microviewer/cursors/small.png
microviewer_cli/__init__.py
microviewer_cli/cli.py
microviewer-1.18.0.dist-info/AUTHORS
microviewer-1.18.0.dist-info/LICENSE
microviewer-1.18.0.dist-info/METADATA
microviewer-1.18.0.dist-info/WHEEL
microviewer-1.18.0.dist-info/entry_points.txt
microviewer-1.18.0.dist-info/pbr.json
microviewer-1.18.0.dist-info/top_level.txt
microviewer-1.18.0.dist-info/RECORD
