Metadata-Version: 2.2
Name: microviewer
Version: 1.18.0
Summary: Visualize 3D numpy arrays in the browser.
Home-page: https://github.com/seung-lab/microviewer/
Author: William Silversmith
Author-email: ws9@princeton.edu
License: License :: OSI Approved :: GNU Lesser General Public License v2 or later (LGPLv2+)
Classifier: Intended Audience :: Developers
Classifier: Development Status :: 4 - Beta
Classifier: License :: OSI Approved :: GNU Lesser General Public License v2 or later (LGPLv2+)
Classifier: Programming Language :: Python
Classifier: Programming Language :: Python :: 3
Classifier: Programming Language :: Python :: 3.9
Classifier: Programming Language :: Python :: 3.10
Classifier: Programming Language :: Python :: 3.11
Classifier: Programming Language :: Python :: 3.12
Classifier: Programming Language :: Python :: 3.13
Classifier: Topic :: Utilities
Classifier: Topic :: Scientific/Engineering :: Image Processing
License-File: LICENSE
License-File: AUTHORS
Requires-Dist: click
Requires-Dist: numpy
Provides-Extra: nii
Requires-Dist: nibabel; extra == "nii"
Provides-Extra: nrrd
Requires-Dist: pynrrd; extra == "nrrd"
Provides-Extra: ckl
Requires-Dist: crackle-codec; extra == "ckl"
Provides-Extra: jxl
Requires-Dist: imagecodecs; extra == "jxl"
Provides-Extra: all-formats
Requires-Dist: nibabel; extra == "all-formats"
Requires-Dist: pynrrd; extra == "all-formats"
Requires-Dist: crackle-codec; extra == "all-formats"
Requires-Dist: imagecodecs; extra == "all-formats"
Provides-Extra: objects
Requires-Dist: vtk; extra == "objects"
Provides-Extra: all
Requires-Dist: nibabel; extra == "all"
Requires-Dist: pynrrd; extra == "all"
Requires-Dist: crackle-codec; extra == "all"
Requires-Dist: imagecodecs; extra == "all"
Requires-Dist: vtk; extra == "all"
Dynamic: author
Dynamic: author-email
Dynamic: classifier
Dynamic: description
Dynamic: description-content-type
Dynamic: home-page
Dynamic: license
Dynamic: provides-extra
Dynamic: requires-dist
Dynamic: summary
